setup.py
Pystamp.egg-info/PKG-INFO
Pystamp.egg-info/SOURCES.txt
Pystamp.egg-info/dependency_links.txt
Pystamp.egg-info/namespace_packages.txt
Pystamp.egg-info/not-zip-safe
Pystamp.egg-info/top_level.txt
pystamp/__init__.py
pystamp/pystamp.py
pystamp/test.py