Metadata-Version: 1.0
Name: Pystamp
Version: 0.0.1
Summary: datetime formatting for human
Home-page: https://github.com/dqminh/pystamp/
Author: Daniel, Dao Quang Minh
Author-email: dqminh89@gmail.com
License: BSD
Platform: any
Classifier: Development Status :: 4 - Beta
Classifier: Environment :: Web Environment
Classifier: Intended Audience :: Developers
Classifier: License :: OSI Approved :: BSD License
Classifier: Operating System :: OS Independent
Classifier: Programming Language :: Python
Classifier: Topic :: Internet :: WWW/HTTP :: Dynamic Content
Classifier: Topic :: Software Development :: Libraries :: Python Modules
